home_journal/__init__.py
home_journal/__main__.py
home_journal/cli.py
home_journal/run.py
home_journal/utils.py
home_journal/site/css/beer.min.css
home_journal/site/css/github-markdown.css
home_journal/site/css/material-symbols-outlined.woff2
home_journal/site/css/roboto-flex-cyrillic-ext.woff2
home_journal/site/css/roboto-flex-cyrillic.woff2
home_journal/site/css/roboto-flex-greek.woff2
home_journal/site/css/roboto-flex-latin-ext.woff2
home_journal/site/css/roboto-flex-latin.woff2
home_journal/site/css/roboto-flex-vietnamese.woff2
home_journal/site/css/site.css
home_journal/site/icons/icon-0.png
home_journal/site/icons/icon-1.png
home_journal/site/icons/icon-2.png
home_journal/site/icons/icon-3.png
home_journal/site/icons/icon-4.png
home_journal/site/icons/icon-5.png
home_journal/site/icons/icon-6.png
home_journal/site/icons/icon-7.png
home_journal/site/icons/icon-8.png
home_journal/site/js/beer.min.js
home_journal/site/js/lightense.min.js
home_journal/site/js/material-dynamic-colors.min.js
home_journal/site/js/new.js
home_journal/site/js/post.js
home_journal/site/js/site.js
home_journal/templates/index.html.j2
home_journal/templates/new.html.j2
home_journal/templates/post.html.j2
home_journal/templates/post.md.j2
reminisce-0.0.7.dist-info/LICENSE
reminisce-0.0.7.dist-info/METADATA
reminisce-0.0.7.dist-info/WHEEL
reminisce-0.0.7.dist-info/entry_points.txt
reminisce-0.0.7.dist-info/top_level.txt
reminisce-0.0.7.dist-info/RECORD
